pybitlaunch/Account.py
pybitlaunch/BaseAPI.py
pybitlaunch/Client.py
pybitlaunch/CreateOptions.py
pybitlaunch/SSHKeys.py
pybitlaunch/Servers.py
pybitlaunch/Transactions.py
pybitlaunch/__init__.py
pybitlaunch-1.1.0.dist-info/LICENSE
pybitlaunch-1.1.0.dist-info/METADATA
pybitlaunch-1.1.0.dist-info/WHEEL
pybitlaunch-1.1.0.dist-info/top_level.txt
pybitlaunch-1.1.0.dist-info/RECORD
