Metadata-Version: 2.1
Name: pybitlaunch
Version: 1.1.0
Summary: pybitlaunch is a python client library for accessing the BitLaunch API.
Home-page: https://github.com/bitlaunchio/pybitlaunch
Author: BitLaunch
Author-email: support@bitlaunch.io
License: UNKNOWN
Platform: UNKNOWN
Classifier: Programming Language :: Python :: 3
Classifier: License :: OSI Approved :: MIT License
Classifier: Operating System :: OS Independent
Requires-Python: >=2.7
